README.md
setup.py
DetectorMorse.egg-info/PKG-INFO
DetectorMorse.egg-info/SOURCES.txt
DetectorMorse.egg-info/dependency_links.txt
DetectorMorse.egg-info/requires.txt
DetectorMorse.egg-info/top_level.txt
detectormorse/__init__.py
detectormorse/__main__.py
detectormorse/detector.py
detectormorse/ptbtokenizer.py
detectormorse/models/DM-wsj.json.gz