Metadata-Version: 2.1
Name: DetectorMorse
Version: 0.4.0
Summary: DetectorMorse, a sentence splitter
Home-page: UNKNOWN
Author: Kyle Gorman
Author-email: kylebgorman@gmail.com
License: UNKNOWN
Platform: UNKNOWN
